[
  {
    "id": "econ102-w5-11",
    "type": "choice",
    "question": "The fourth step in calculating the inflation rate, after determining the basket, collecting prices, and calculating the cost of the basket, is to:",
    "options": [
      "Divide the nominal GDP by the real GDP",
      "Calculate the percentage change in the price index from the previous period",
      "Subtract the inflation rate from the nominal interest rate",
      "Adjust the basket for quality improvements and new products"
    ],
    "answer": "B",
    "analysis": {
      "solution": "计算通货膨胀率的第四个也是最后一个步骤是计算物价指数较前一期的百分比变化。",
      "decoding": [
        "题干列出了计算通胀的前三个步骤：确定一篮子商品、收集价格、计算总成本 。",
        "要求识别标准流程中的最后一个步骤 。"
      ],
      "conditions": [
        {
          "title": "通货膨胀率公式",
          "content": "$\\text{Inflation Rate} = \\frac{\\text{Price Level}_{\\text{this year}} - \\text{Price Level}_{\\text{last year}}}{\\text{Price Level}_{\\text{last year}}} \\times 100$%",
          "description": "这是衡量物价水平随时间变化的百分比增长率 。"
        }
      ],
      "traps": [
        {
          "title": "步骤混淆陷阱",
          "description": "学生容易把\"调整篮子\"（处理偏差的方法）或\"计算利率\"误当作计算通胀率本身的步骤。"
        }
      ],
      "steps": [
        {
          "title": "回顾计算流程",
          "content": "资料显示计算分为四步：1.确定商品；2.收集价格；3.计算总成本；4.计算百分比变化 。",
          "tag": "逻辑拆解"
        },
        {
          "title": "定位第四步",
          "content": "在获得不同年份的成本或指数后，通过计算变化率得出通货膨胀率 。",
          "tag": "结论"
        },
        {
          "title": "验证结论",
          "content": "选项 B 准确对应了这一数学操作过程。",
          "tag": "结论"
        }
      ],
      "option_analysis": [
        {
          "label": "A",
          "reason": "错误点：这是计算 GDP 平减指数的方法。正确概念：CPI 通胀率基于固定一篮子商品的成本变化 。"
        },
        {
          "label": "C",
          "reason": "错误点：这是计算实际利率的费雪公式。正确概念：它用于调整利率而非计算物价指数 。"
        },
        {
          "label": "D",
          "reason": "错误点：这是克服 CPI 局限性的建议。正确概念：标准的 CPI 计算步骤中假设篮子是固定的 。"
        }
      ]
    },
    "knowledge_points": [
      "Calculation of Inflation Rate",
      "Consumer Price Index (CPI)",
      "Price Level"
    ],
    "source": "Lecture"
  },
  {
    "id": "econ102-w5-12",
    "type": "choice",
    "question": "Policymakers often track 'core inflation' rather than headline inflation because core inflation:",
    "options": [
      "Includes only domestically produced goods and services",
      "Excludes volatile food and energy prices to reveal underlying trends",
      "Directly measures the change in the producer's input costs",
      "Adjusts for substitution bias and quality improvements automatically"
    ],
    "answer": "B",
    "analysis": {
      "solution": "核心通胀（Core inflation）通过剔除价格波动剧烈的食品和能源，帮助观察通胀的潜在趋势 。",
      "decoding": [
        "题干探讨追踪\"核心通胀\"而非\"整体通胀\"的原因。",
        "核心在于区分不同通胀指标的构成和用途 。"
      ],
      "conditions": [
        {
          "title": "核心通胀定义",
          "content": "$\\text{Core Inflation} = \\text{Headline CPI} - (\\text{Food} + \\text{Energy})$",
          "description": "旨在消除暂时性的价格扰动，反映长期的价格压力 。"
        }
      ],
      "traps": [
        {
          "title": "指标范畴陷阱",
          "description": "学生常认为核心通胀包含所有商品。实际上它特意剔除了某些类别以提高预测准确性。"
        }
      ],
      "steps": [
        {
          "title": "识别波动因素",
          "content": "食品和能源价格受季节和国际局势影响极大，波动频繁 。",
          "tag": "逻辑拆解"
        },
        {
          "title": "分析政策需求",
          "content": "政策制定者需要过滤这些\"噪音\"，以便观察整体物价是否在持续上升 。",
          "tag": "逻辑拆解"
        },
        {
          "title": "匹配定义",
          "content": "排除波动项以观察潜在趋势正是核心通胀的功能，对应选项 B。",
          "tag": "结论"
        }
      ],
      "option_analysis": [
        {
          "label": "A",
          "reason": "错误点：这是 GDP 平减指数的特征。正确概念：核心通胀仍属于 CPI 范畴，包含进口消费品 。"
        },
        {
          "label": "C",
          "reason": "错误点：这是 PPI 的职能。正确概念：核心通胀衡量的是消费端的潜在物价变动 。"
        },
        {
          "label": "D",
          "reason": "错误点：核心通胀并未解决 CPI 的技术偏差。正确概念：它解决的是分类波动问题而非统计偏差 。"
        }
      ]
    },
    "knowledge_points": [
      "Core Inflation",
      "Headline Inflation",
      "Price Stability"
    ],
    "source": "Notes"
  },
  {
    "id": "econ102-w5-13",
    "type": "choice",
    "question": "A worker receives a 3% nominal wage increase during a year when the inflation rate is 5%. If the worker feels richer because of the extra dollars in their paycheck, they are experiencing:",
    "options": [
      "The inflation fallacy",
      "Menu costs",
      "Money illusion",
      "Shoe-leather costs"
    ],
    "answer": "C",
    "analysis": {
      "solution": "货币幻觉（Money illusion）指人们倾向于关注名义金额而忽视通胀调整后的实际购买力 。",
      "decoding": [
        "名义工资涨幅（3%）小于通胀率（5%），意味着实际工资下降了 。",
        "员工\"觉得更富有\"反映了对名义数值的盲目关注 。"
      ],
      "conditions": [
        {
          "title": "实际工资变动公式",
          "content": "$\\Delta \\text{Real Wage} \\approx \\Delta \\text{Nominal Wage} - \\text{Inflation Rate}$%",
          "description": "用于判断劳动者真实生活水平的提升或下降 。"
        }
      ],
      "traps": [
        {
          "title": "概念辨析陷阱",
          "description": "学生极易混淆\"货币幻觉\"与\"通胀谬误\"。前者是看重名义钱数，后者是认为通胀一定会降低购买力 。"
        }
      ],
      "steps": [
        {
          "title": "计算实际购买力变化",
          "content": "$3\\% - 5\\% = -2\\%$。工人的实际购买力实际上是下降了 。",
          "tag": "计算"
        },
        {
          "title": "识别心理反应",
          "content": "尽管变穷了，工人却因为名义金额增加而感到富有，这忽略了物价上涨的影响 。",
          "tag": "逻辑拆解"
        },
        {
          "title": "锁定术语",
          "content": "这种对名义金额的偏好即为 Money illusion 。",
          "tag": "结论"
        }
      ],
      "option_analysis": [
        {
          "label": "A",
          "reason": "错误点：这是认为通胀必损购买力的错误看法。正确概念：工人此处是\"没意识到\"损失，而非\"夸大\"损失 。"
        },
        {
          "label": "B",
          "reason": "错误点：这是企业调价的成本。正确概念：它属于生产者的物理成本，而非工人的心理偏差 。"
        },
        {
          "label": "D",
          "reason": "错误点：这是持有现金的精力成本。正确概念：它涉及的是减少持币的行为，而非认知的偏差 。"
        }
      ]
    },
    "knowledge_points": [
      "Money Illusion",
      "Nominal vs. Real Wages",
      "Real Interest Rate"
    ],
    "source": "Textbook"
  },
  {
    "id": "econ102-w5-14",
    "type": "choice",
    "question": "Which of the following scenarios best illustrates the 'menu costs' of inflation?",
    "options": [
      "A person spends two hours every week transferring money to avoid losing value on cash.",
      "A restaurant owner has to hire a printing service to update the prices on all physical menus.",
      "A construction company incorrectly expands production because it thinks the demand for its houses has increased.",
      "A lender receives payments that are worth less in terms of purchasing power than expected."
    ],
    "answer": "B",
    "analysis": {
      "solution": "菜单成本（Menu costs）指卖家调整价格时产生的边际成本，如重印菜单 。",
      "decoding": [
        "题干要求识别\"菜单成本\"的具体情景 。",
        "核心特征是企业调整标价的行政或物理支出 。"
      ],
      "conditions": [
        {
          "title": "菜单成本属性",
          "content": "$\\text{Menu Costs} \\in \\text{Expected Inflation Costs}$",
          "description": "当物价上涨时，企业必须花费资源更新标签和系统信息 。"
        }
      ],
      "traps": [
        {
          "title": "成本主体陷阱",
          "description": "学生容易把所有通胀带来的麻烦都当成菜单成本。需区分买家（皮鞋）和卖家（菜单）。"
        }
      ],
      "steps": [
        {
          "title": "识别经济行为主体",
          "content": "菜单成本的承担者是提供商品或服务的企业（卖家） 。",
          "tag": "逻辑拆解"
        },
        {
          "title": "分析成本具体形式",
          "content": "调整价格涉及重印、系统更新、人员劳动等实际支出 。",
          "tag": "逻辑拆解"
        },
        {
          "title": "验证选项",
          "content": "餐厅重印菜单是该概念最直观、最经典的体现，对应 B 。",
          "tag": "结论"
        }
      ],
      "option_analysis": [
        {
          "label": "A",
          "reason": "错误点：这是买家减少贬值损失的努力。正确概念：这是 Shoe-leather costs 。"
        },
        {
          "label": "C",
          "reason": "错误点：这是对市场信号的误判。正确概念：这是 Confused price signals 。"
        },
        {
          "label": "D",
          "reason": "错误点：这是财富的转移效应。正确概念：这是 Redistribution of wealth 。"
        }
      ]
    },
    "knowledge_points": [
      "Menu Costs",
      "Costs of Inflation",
      "Expected Inflation"
    ],
    "source": "Lecture"
  },
  {
    "id": "econ102-w5-15",
    "type": "choice",
    "question": "Money's ability to transfer wealth from the present to the future is known as its function as a:",
    "options": [
      "Medium of exchange",
      "Unit of account",
      "Store of value",
      "Method of barter"
    ],
    "answer": "C",
    "analysis": {
      "solution": "货币将财富转移到未来的职能被称为价值储藏（Store of value） 。",
      "decoding": [
        "考察货币三大核心职能之一的定义 。",
        "关键词是\"跨期转移财富\" 。"
      ],
      "conditions": [
        {
          "title": "价值储藏要求",
          "content": "$\\text{Store of Value} \\implies \\text{Reliability over Time}$",
          "description": "要发挥此作用，货币必须容易储存且能随时间推移保值 。"
        }
      ],
      "traps": [
        {
          "title": "职能重叠陷阱",
          "description": "学生常认为买东西也是转移价值。但\"买东西\"是当下的交换，而\"存着不花\"才是储藏。"
        }
      ],
      "steps": [
        {
          "title": "确定职能维度",
          "content": "题目强调的是\"时间轴\"上的财富保留 。",
          "tag": "逻辑拆解"
        },
        {
          "title": "对比定义",
          "content": "计价单位是衡量价值，交易媒介是当下买卖，价值储藏是保留至未来 。",
          "tag": "逻辑拆解"
        },
        {
          "title": "得出结论",
          "content": "对应 Store of value 职能，选项 C 正确 。",
          "tag": "结论"
        }
      ],
      "option_analysis": [
        {
          "label": "A",
          "reason": "错误点：侧重于当前的流通。正确概念：这是用于购买商品或劳动的职能 。"
        },
        {
          "label": "B",
          "reason": "错误点：侧重于价格的衡量标准。正确概念：这是提供衡量经济价值共同单位的职能 。"
        },
        {
          "label": "D",
          "reason": "错误点：这是货币出现之前的交换形式。正确概念：物物交换存在\"双重需求巧合\"难题 。"
        }
      ]
    },
    "knowledge_points": [
      "Functions of Money",
      "Store of Value"
    ],
    "source": "Textbook"
  },
  {
    "id": "econ102-w5-16",
    "type": "choice",
    "question": "How does 'new product bias' affect the accuracy of the CPI in measuring the true cost of living?",
    "options": [
      "It causes CPI to underestimate inflation because new products are initially very expensive.",
      "It causes CPI to overestimate the cost of living because new products often lower the cost of achieving a certain standard of living.",
      "It has no effect because CPI is updated every month to include all new inventions.",
      "It causes CPI to fluctuate randomly depending on which new products are popular."
    ],
    "answer": "B",
    "analysis": {
      "solution": "新产品偏误（New product bias）导致 CPI 高估生活成本，因为新产品往往能以更低成本提高生活质量，但未被固定篮子及时包含 。",
      "decoding": [
        "探讨 CPI 局限性中的\"新产品\"因素 。",
        "核心矛盾在于\"固定一揽子商品\"与\"动态市场\"之间的脱节 。"
      ],
      "conditions": [
        {
          "title": "CPI 偏差方向",
          "content": "$\\text{CPI} > \\text{True Cost of Living Adjustment}$",
          "description": "由于计算逻辑的局限，CPI 通常会高估生活成本的变化 。"
        }
      ],
      "traps": [
        {
          "title": "偏差方向陷阱",
          "description": "学生可能错误认为新产品太贵会拉低 CPI。实际上新产品的引入是降低了\"维持同等生活水平\"的代价 。"
        }
      ],
      "steps": [
        {
          "title": "分析新产品作用",
          "content": "新产品的引入（如网络流媒体取代昂贵的影碟）实际上降低了人们的开支 。",
          "tag": "逻辑拆解"
        },
        {
          "title": "核查 CPI 计算方式",
          "content": "CPI 使用固定篮子，在这些新产品被正式纳入之前，它忽略了这种成本下降 。",
          "tag": "逻辑拆解"
        },
        {
          "title": "确定偏差性质",
          "content": "因此，由于未能及时反映生活成本的这种降低，CPI 的数值会显得偏高，即 Overestimate 。",
          "tag": "结论"
        }
      ],
      "option_analysis": [
        {
          "label": "A",
          "reason": "错误点：偏差方向判断错误。正确概念：CPI 的三大局限性通常都导致它高估（Overestimate）通胀 。"
        },
        {
          "label": "C",
          "reason": "错误点：事实陈述错误。正确概念：CPI 追踪的是固定的一揽子商品，更新频率不足以实时涵盖新发明 。"
        },
        {
          "label": "D",
          "reason": "错误点：偏差具有系统性。正确概念：偏差主要源于固定的统计结构，而非随机波动 。"
        }
      ]
    },
    "knowledge_points": [
      "New Product Bias",
      "CPI Challenges",
      "Cost of Living"
    ],
    "source": "Mixed"
  },
  {
    "id": "econ102-w5-17",
    "type": "bool",
    "question": "Hyperinflation is characterized by such high inflation rates that money loses its ability to serve as a medium of exchange, unit of account, and store of value.",
    "answer": true,
    "analysis": {
      "solution": "正确。在恶性通货膨胀（Hyperinflation）下，物价上涨极快，货币的所有职能都会遭到严重侵蚀甚至丧失 。",
      "decoding": [
        "考察恶性通胀对货币职能的极端破坏性 。",
        "判断\"失去所有职能\"是否符合恶性通胀的描述 。"
      ],
      "conditions": [
        {
          "title": "恶性通胀影响",
          "content": "$\\text{Hyperinflation} \\implies \\text{Collapse of Monetary Functions}$",
          "description": "当通胀失控，人们会转向物物交换或其他货币，原生货币的功能归零 。"
        }
      ],
      "traps": [
        {
          "title": "职能残留陷阱",
          "description": "学生可能认为只要是钱就还有职能。但在恶性通胀下，钱可能连纸都不如，没人愿意用它标价或交易 。"
        }
      ],
      "steps": [
        {
          "title": "分析价值储藏职能",
          "content": "由于物价每小时都在涨，存钱意味着财富瞬间蒸发，该职能率先失效 。",
          "tag": "逻辑拆解"
        },
        {
          "title": "分析交易与计价职能",
          "content": "由于价格变动太快，商家无法标价（计价失效），个人拒绝接收该货币（交易失效） 。",
          "tag": "逻辑拆解"
        },
        {
          "title": "得出判断",
          "content": "恶性通胀确实会侵蚀货币的所有职能，如委内瑞拉的例子 。",
          "tag": "结论"
        }
      ]
    },
    "knowledge_points": [
      "Hyperinflation",
      "Functions of Money",
      "Monetary Collapse"
    ],
    "source": "Notes"
  },
  {
    "id": "econ102-w5-18",
    "type": "bool",
    "question": "When the inflation rate is positive, nominal GDP will always grow faster than real GDP.",
    "answer": true,
    "analysis": {
      "solution": "正确。只要通货膨胀率为正，物价水平就在上升，名义 GDP（含物价变动）的增长率必然高于剔除了物价变动的实际 GDP 。",
      "decoding": [
        "比较名义变量与实际变量在通胀环境下的增长速度 。",
        "通胀率为正意味着物价指数（Deflator）在变大 。"
      ],
      "conditions": [
        {
          "title": "GDP 增长关系",
          "content": "$\\Delta \\text{Nominal GDP} \\approx \\Delta \\text{Real GDP} + \\text{Inflation Rate}$%",
          "description": "名义增长包含了产量的增长和价格的上涨 。"
        }
      ],
      "traps": [
        {
          "title": "通货紧缩误判",
          "description": "若通胀率为负（通缩），则结论相反。学生需注意题干限定了\"positive\"通胀率 。"
        }
      ],
      "steps": [
        {
          "title": "定义名义与实际",
          "content": "名义 GDP 用当前价格计算；实际 GDP 用基期价格计算，剔除了通胀因素 。",
          "tag": "逻辑拆解"
        },
        {
          "title": "分析通胀影响",
          "content": "通胀率为正表示价格逐年上涨，因此同样的产出在名义上会显得更多 。",
          "tag": "逻辑拆解"
        },
        {
          "title": "得出结论",
          "content": "因此，名义 GDP 的增长包含了实际产出增长加上价格上涨部分，必然更快 。",
          "tag": "结论"
        }
      ]
    },
    "knowledge_points": [
      "Nominal vs. Real GDP",
      "GDP Deflator",
      "Inflation Impact"
    ],
    "source": "Lecture"
  },
  {
    "id": "econ102-w5-19",
    "type": "essay",
    "question": "Suppose a 'representative basket' consists of 2 loaves of bread and 3 gallons of milk. In Year 1, bread costs 2.00 $/loaf and milk costs 3.00 $/gallon. In Year 2, bread costs 2.50 $/loaf and milk costs 4.00 $/gallon. \\n1. Calculate the cost of the basket in Year 1 and Year 2. \\n2. Calculate the inflation rate between Year 1 and Year 2.",
    "answer": "The cost of the basket in Year 1 is 13.00, $ and \\in Year 2 it is 17.00. $ The inflation rate is 30.77%.",
    "analysis": {
      "decoding": [
        "篮子构成（固定）：2 面包 + 3 牛奶 。",
        "第 1 年价格：面包 2.0 $0$，牛奶 3.0 $0$。",
        "第 2 年价格：面包 2.5 $0$，牛奶 4.0 $0$。",
        "任务：计算每年的总成本并求百分比变化 。"
      ],
      "conditions": [
        {
          "title": "篮子总成本公式",
          "content": "$\\text{Cost} = (P_{\\text{bread}} \\times Q_{\\text{bread}}) + (P_{\\text{milk}} \\times Q_{\\text{milk}})$",
          "description": "这是计算物价指数的基础步骤，保持数量 $Q$ 不变 。"
        },
        {
          "title": "通胀率计算公式",
          "content": "$\\pi = \\frac{\\text{Cost}_{Y2} - \\text{Cost}_{Y1}}{\\text{Cost}_{Y1}} \\times 100$%",
          "description": "衡量固定篮子成本的百分比增长 。"
        }
      ],
      "traps": [
        {
          "title": "数量变动陷阱",
          "description": "学生有时会错误地尝试更新篮子里的数量。注意 CPI 的定义必须使用固定数量（Fixed quantity） 。"
        }
      ],
      "steps": [
        {
          "title": "计算 Year 1 总成本",
          "content": "$\\text{Cost}_{Y1} = (2 \\times 2.00) + (3 \\times 3.00) = 4.00 + 9.00 = 13.00$。",
          "tag": "计算"
        },
        {
          "title": "计算 Year 2 总成本",
          "content": "$\\text{Cost}_{Y2} = (2 \\times 2.50) + (3 \\times 4.00) = 5.00 + 12.00 = 17.00$。",
          "tag": "计算"
        },
        {
          "title": "计算通货膨胀率",
          "content": "$\\text{Rate} = \\frac{17.00 - 13.00}{13.00} = \\frac{4.00}{13.00} \\approx 30.77$%。",
          "tag": "结论"
        }
      ]
    },
    "knowledge_points": [
      "CPI Calculation",
      "Inflation Rate",
      "Fixed Basket of Goods"
    ],
    "source": "Mixed"
  },
  {
    "id": "econ102-w5-20",
    "type": "essay",
    "question": "A corn farmer notices that the market price of corn has risen by 10%. He mistakenly assumes this is purely due to a huge increase in demand for his corn and decides to double his production. However, in reality, all prices in the economy (including his costs) have risen by 10% due to general inflation. \\n1. Which cost of inflation does this scenario describe? \\n2. Explain why this leads to an inefficient allocation of resources in the economy.",
    "answer": "This scenario describes 'confused price signals'. It leads to inefficiency because the producer expands supply based on a nominal price increase, rather than a real change in relative demand, resulting in an overproduction of corn.",
    "analysis": {
      "decoding": [
        "农民看到玉米价格上涨 10% 。",
        "误判原因：认为是需求增加（相对价格变动），实际是普遍通胀（物价水平变动） 。",
        "任务：识别术语并分析经济后果 。"
      ],
      "conditions": [
        {
          "title": "价格信号混淆",
          "content": "$\\text{Total Inflation} \\neq \\Delta \\text{Relative Demand}$",
          "description": "价格本应引导资源流向需求最高的地方，但通胀会让信号变得模糊 。"
        }
      ],
      "traps": [
        {
          "title": "通胀谬误辨析",
          "description": "虽然涉及认知错误，但重点不在于购买力被毁，而在于\"价格作为生产指导信号\"的失效 。"
        }
      ],
      "steps": [
        {
          "title": "识别通胀成本类型",
          "content": "资料指出，当普遍物价上涨让生产者误以为是需求增加并据此决策时，这属于 Confused price signals 。",
          "tag": "逻辑拆解"
        },
        {
          "title": "分析农民的决策逻辑",
          "content": "农民看到了名义价格上升，但因为忽视了成本也在涨，其真实利润空间并未扩大 。",
          "tag": "逻辑拆解"
        },
        {
          "title": "阐述资源配置后果",
          "content": "社会并不需要更多的玉米，但由于信号被通胀扭曲，农民投入了过多资源（如土地、化肥），造成了生产过剩和资源浪费 。",
          "tag": "结论"
        }
      ]
    },
    "knowledge_points": [
      "Confused Price Signals",
      "Unexpected Inflation",
      "Resource Allocation"
    ],
    "source": "Mixed"
  }
]